{"loss": 9.123290061950684, "accuracy": 27.13758659362793, "timestamp": 1736833511, "checkpoint_dir_name": null, "done": false, "training_iteration": 1, "trial_id": "c0fc91d1", "date": "2025-01-14_05-45-11", "time_this_iter_s": 1177.6152062416077, "time_total_s": 1177.6152062416077, "pid": 715123, "hostname": "22bb28869fb9", "node_ip": "172.17.0.2", "config": {"learning_rate": 0.001, "hidden_threshold": 16.163010691121553, "fast_sigmoid_slope": 20, "opt_beta_1": 0.9, "opt_beta_2": 0.99, "bits": 5}, "time_since_restore": 1177.6152062416077, "iterations_since_restore": 1}
{"loss": 1.4926443099975586, "accuracy": 32.51953125, "timestamp": 1736834680, "checkpoint_dir_name": null, "done": false, "training_iteration": 2, "trial_id": "c0fc91d1", "date": "2025-01-14_06-04-40", "time_this_iter_s": 1169.0889656543732, "time_total_s": 2346.704171895981, "pid": 715123, "hostname": "22bb28869fb9", "node_ip": "172.17.0.2", "config": {"learning_rate": 0.001, "hidden_threshold": 16.163010691121553, "fast_sigmoid_slope": 20, "opt_beta_1": 0.9, "opt_beta_2": 0.99, "bits": 5}, "time_since_restore": 2346.704171895981, "iterations_since_restore": 2}
{"loss": 1.5281144380569458, "accuracy": 30.322265625, "timestamp": 1736835849, "checkpoint_dir_name": null, "done": false, "training_iteration": 3, "trial_id": "c0fc91d1", "date": "2025-01-14_06-24-09", "time_this_iter_s": 1169.5214858055115, "time_total_s": 3516.2256577014923, "pid": 715123, "hostname": "22bb28869fb9", "node_ip": "172.17.0.2", "config": {"learning_rate": 0.001, "hidden_threshold": 16.163010691121553, "fast_sigmoid_slope": 20, "opt_beta_1": 0.9, "opt_beta_2": 0.99, "bits": 5}, "time_since_restore": 3516.2256577014923, "iterations_since_restore": 3}
{"loss": 1.5058735609054565, "accuracy": 31.65690040588379, "timestamp": 1736837018, "checkpoint_dir_name": null, "done": false, "training_iteration": 4, "trial_id": "c0fc91d1", "date": "2025-01-14_06-43-38", "time_this_iter_s": 1169.0157053470612, "time_total_s": 4685.2413630485535, "pid": 715123, "hostname": "22bb28869fb9", "node_ip": "172.17.0.2", "config": {"learning_rate": 0.001, "hidden_threshold": 16.163010691121553, "fast_sigmoid_slope": 20, "opt_beta_1": 0.9, "opt_beta_2": 0.99, "bits": 5}, "time_since_restore": 4685.2413630485535, "iterations_since_restore": 4}
{"loss": 1.544501781463623, "accuracy": 30.99500846862793, "timestamp": 1736838207, "checkpoint_dir_name": null, "done": true, "training_iteration": 5, "trial_id": "c0fc91d1", "date": "2025-01-14_07-03-27", "time_this_iter_s": 1189.0732703208923, "time_total_s": 5874.314633369446, "pid": 715123, "hostname": "22bb28869fb9", "node_ip": "172.17.0.2", "config": {"learning_rate": 0.001, "hidden_threshold": 16.163010691121553, "fast_sigmoid_slope": 20, "opt_beta_1": 0.9, "opt_beta_2": 0.99, "bits": 5}, "time_since_restore": 5874.314633369446, "iterations_since_restore": 5}
